[
  {
    "email": "labs@gatewaymobilephlebotomy.com",
    "name": "Gateway Mobile Phlebotomy",
    "campaign": "survey-biggest-challenge-2026-03",
    "sentAt": "2026-03-10T12:00:00.000Z",
    "status": "sent"
  },
  {
    "email": "imphlebotomy25@gmail.com",
    "name": "Illumination Mobile Phlebotomy",
    "campaign": "survey-biggest-challenge-2026-03",
    "sentAt": "2026-03-10T12:00:00.000Z",
    "status": "sent"
  },
  {
    "email": "info@poncemobilephlebotomy.com",
    "name": "Ponce Mobile Phlebotomy",
    "campaign": "survey-biggest-challenge-2026-03",
    "sentAt": "2026-03-10T12:00:00.000Z",
    "status": "sent"
  },
  {
    "email": "sticksandneedlesllc@gmail.com",
    "name": "STICKS & NEEDLES MOBILE LAB LLC",
    "campaign": "survey-biggest-challenge-2026-03",
    "sentAt": "2026-03-10T12:00:00.000Z",
    "status": "sent"
  },
  {
    "email": "egmphlebotomy@gmail.com",
    "name": "EverGreene Mobile Phlebotomy",
    "campaign": "survey-biggest-challenge-2026-03",
    "sentAt": "2026-03-10T12:00:00.000Z",
    "status": "sent"
  },
  {
    "email": "salinasmith21@gmail.com",
    "name": "Salina's Mobile Phlebotomist & Healthcare service",
    "campaign": "survey-biggest-challenge-2026-03",
    "sentAt": "2026-03-10T12:00:00.000Z",
    "status": "sent"
  },
  {
    "email": "banksglenda1@yahoo.com",
    "name": "LB DIAGNOSTIC LABORATORY LLC",
    "campaign": "survey-biggest-challenge-2026-03",
    "sentAt": "2026-03-10T12:00:00.000Z",
    "status": "sent"
  },
  {
    "email": "cbarrera@cmbgroupny.com",
    "name": "CMB Group",
    "campaign": "survey-biggest-challenge-2026-03",
    "sentAt": "2026-03-10T12:00:00.000Z",
    "status": "sent"
  },
  {
    "email": "admin@optimalparamedicalexams.com",
    "name": "Optimal Paramedical Exams, LLC",
    "campaign": "survey-biggest-challenge-2026-03",
    "sentAt": "2026-03-10T12:00:00.000Z",
    "status": "sent"
  },
  {
    "email": "support@bandrtraining.com",
    "name": "Butterflies & Rainbows Training LLC",
    "campaign": "survey-biggest-challenge-2026-03",
    "sentAt": "2026-03-10T12:00:00.000Z",
    "status": "sent"
  },
  {
    "email": "ameshia@onesticknola.com",
    "name": "one stick that's it lab",
    "campaign": "survey-biggest-challenge-2026-03",
    "sentAt": "2026-03-10T12:00:00.000Z",
    "status": "sent"
  },
  {
    "email": "info@ubersticksmedical.com",
    "name": "UBERSTICKS MEDICAL LLC",
    "campaign": "survey-biggest-challenge-2026-03",
    "sentAt": "2026-03-10T12:00:00.000Z",
    "status": "sent"
  },
  {
    "email": "info@milehighdtc.com",
    "name": "Mile High Drug Test Consultants",
    "campaign": "survey-biggest-challenge-2026-03",
    "sentAt": "2026-03-10T12:00:00.000Z",
    "status": "sent"
  },
  {
    "email": "allstarphlebotomy@gmail.com",
    "name": "Allstar Phlebotomy LLC",
    "campaign": "survey-biggest-challenge-2026-03",
    "sentAt": "2026-03-10T12:00:00.000Z",
    "status": "sent"
  },
  {
    "email": "statspdt@gmail.com",
    "name": "Stats Phlebotomy and Drug Testing",
    "campaign": "survey-biggest-challenge-2026-03",
    "sentAt": "2026-03-10T12:00:00.000Z",
    "status": "sent"
  },
  {
    "email": "lcallen@prostiksolutions.com",
    "name": "ProStik Solutions",
    "campaign": "survey-biggest-challenge-2026-03",
    "sentAt": "2026-03-10T12:00:00.000Z",
    "status": "sent"
  },
  {
    "email": "lab@cpclabsanywhere.com",
    "name": "Compassion Care Phlebotomy",
    "campaign": "survey-biggest-challenge-2026-03",
    "sentAt": "2026-03-10T12:00:00.000Z",
    "status": "sent"
  },
  {
    "email": "starrmobileblooddraw@gmail.com",
    "name": "MobileBloodDraw",
    "campaign": "survey-biggest-challenge-2026-03",
    "sentAt": "2026-03-10T12:00:00.000Z",
    "status": "sent"
  },
  {
    "email": "vibrancescreeningandwell@gmail.com",
    "name": "Vibrance Screening and Wellness",
    "campaign": "survey-biggest-challenge-2026-03",
    "sentAt": "2026-03-10T12:00:00.000Z",
    "status": "sent"
  },
  {
    "email": "mdcmobilephlebotomy@yahoo.com",
    "name": "MDC Mobile Phlebotomy & Rural Health Services",
    "campaign": "survey-biggest-challenge-2026-03",
    "sentAt": "2026-03-10T12:00:00.000Z",
    "status": "sent"
  },
  {
    "email": "info@itphlebotomysol.com",
    "name": "I.T. Phlebotomy Solutions",
    "campaign": "survey-biggest-challenge-2026-03",
    "sentAt": "2026-03-10T12:00:00.000Z",
    "status": "sent"
  },
  {
    "email": "proveinphlebotomy22@gmail.com",
    "name": "Pro Vein Mobile Phlebotomy Servic",
    "campaign": "survey-biggest-challenge-2026-03",
    "sentAt": "2026-03-10T12:00:00.000Z",
    "status": "sent"
  },
  {
    "email": "carewithluvshealth@gmail.com",
    "name": "CAREWITHLUVS LLC",
    "campaign": "survey-biggest-challenge-2026-03",
    "sentAt": "2026-03-10T12:00:00.000Z",
    "status": "sent"
  },
  {
    "email": "tamianawheelphlebotomy@gmail.com",
    "name": "Tamiana Wheel Phlebotomy",
    "campaign": "survey-biggest-challenge-2026-03",
    "sentAt": "2026-03-10T12:00:00.000Z",
    "status": "sent"
  },
  {
    "email": "ebonywexam@gmail.com",
    "name": "Choice Mobile Lab",
    "campaign": "survey-biggest-challenge-2026-03",
    "sentAt": "2026-03-10T12:00:00.000Z",
    "status": "sent"
  },
  {
    "email": "boujeesticksco@gmail.com",
    "name": "Boujee Sticks And CO",
    "campaign": "survey-biggest-challenge-2026-03",
    "sentAt": "2026-03-10T12:00:00.000Z",
    "status": "sent"
  },
  {
    "email": "support@accugendiagnostics.com",
    "name": "AccuGen Diagnostics LLC",
    "campaign": "survey-biggest-challenge-2026-03",
    "sentAt": "2026-03-10T12:00:00.000Z",
    "status": "sent"
  },
  {
    "email": "booknow@g4solutions.online",
    "name": "G4 Solutions",
    "campaign": "survey-biggest-challenge-2026-03",
    "sentAt": "2026-03-10T12:00:00.000Z",
    "status": "sent"
  },
  {
    "email": "info@compassionatetouchlab.com",
    "name": "Compassionate Touch Lab ServicesLLC",
    "campaign": "survey-biggest-challenge-2026-03",
    "sentAt": "2026-03-10T12:00:00.000Z",
    "status": "sent"
  },
  {
    "email": "info@treeoflifelabgroup.com",
    "name": "Tree of Life Lab Group",
    "campaign": "survey-biggest-challenge-2026-03",
    "sentAt": "2026-03-10T12:00:00.000Z",
    "status": "sent"
  },
  {
    "email": "maxinechapp@icloud.com",
    "name": "Max's CPR And Medical Training LLC",
    "campaign": "survey-biggest-challenge-2026-03",
    "sentAt": "2026-03-10T12:00:00.000Z",
    "status": "sent"
  },
  {
    "email": "atlmobilphlebotomy@gmail.com",
    "name": "ATL Mobile Phlebotomy/ Houston,TX",
    "campaign": "survey-biggest-challenge-2026-03",
    "sentAt": "2026-03-10T12:00:00.000Z",
    "status": "sent"
  },
  {
    "email": "info@trusttestcollection.com",
    "name": "TrustTest Collection",
    "campaign": "survey-biggest-challenge-2026-03",
    "sentAt": "2026-03-10T12:00:00.000Z",
    "status": "sent"
  },
  {
    "email": "medilabsllc@gmail.com",
    "name": "MediLabs LLC",
    "campaign": "survey-biggest-challenge-2026-03",
    "sentAt": "2026-03-10T12:00:00.000Z",
    "status": "sent"
  },
  {
    "email": "ivliquidlounge@gmail.com",
    "name": "Ideal Vitality Wellness",
    "campaign": "survey-biggest-challenge-2026-03",
    "sentAt": "2026-03-10T12:00:00.000Z",
    "status": "sent"
  },
  {
    "email": "info@gentletouchmobilelabservices.com",
    "name": "Gentle touch mobile lab services",
    "campaign": "survey-biggest-challenge-2026-03",
    "sentAt": "2026-03-10T12:00:00.000Z",
    "status": "sent"
  },
  {
    "email": "info@labservicesinc.com",
    "name": "LabServices Inc",
    "campaign": "survey-biggest-challenge-2026-03",
    "sentAt": "2026-03-10T12:00:00.000Z",
    "status": "sent"
  },
  {
    "email": "morveramedicalllc@gmail.com",
    "name": "Stepdown Medical",
    "campaign": "survey-biggest-challenge-2026-03",
    "sentAt": "2026-03-10T12:00:00.000Z",
    "status": "sent"
  },
  {
    "email": "info@rainelabpros.com",
    "name": "RAINE LAB PROS",
    "campaign": "survey-biggest-challenge-2026-03",
    "sentAt": "2026-03-10T12:00:00.000Z",
    "status": "sent"
  },
  {
    "email": "info@usmobilelab.com",
    "name": "US Mobile Lab",
    "campaign": "survey-biggest-challenge-2026-03",
    "sentAt": "2026-03-10T12:00:00.000Z",
    "status": "sent"
  },
  {
    "email": "corlandra14@aol.com",
    "name": "Crystallized Specimen Collections LLC",
    "campaign": "survey-biggest-challenge-2026-03",
    "sentAt": "2026-03-10T12:00:00.000Z",
    "status": "sent"
  },
  {
    "email": "info@cmbgroupny.com",
    "name": "CMB Group Consulting & Advisory Firm",
    "campaign": "survey-biggest-challenge-2026-03",
    "sentAt": "2026-03-10T12:00:00.000Z",
    "status": "sent"
  },
  {
    "email": "alwaysthereenterprises@gmail.com",
    "name": "Always There Enterprises LLC",
    "campaign": "survey-biggest-challenge-2026-03",
    "sentAt": "2026-03-10T12:00:00.000Z",
    "status": "sent"
  },
  {
    "email": "info@justlittlepoke.com",
    "name": "Just Little Poke Mobile Phlebotomy",
    "campaign": "survey-biggest-challenge-2026-03",
    "sentAt": "2026-03-10T12:00:00.000Z",
    "status": "sent"
  },
  {
    "email": "kterepka@mobilelabspro.com",
    "name": "Mobile Labs Pro",
    "campaign": "survey-biggest-challenge-2026-03",
    "sentAt": "2026-03-10T12:00:00.000Z",
    "status": "sent"
  },
  {
    "email": "info@mobilephlebcare.com",
    "name": "Phlebcare Mobile Lab & DNA Solutions",
    "campaign": "survey-biggest-challenge-2026-03",
    "sentAt": "2026-03-10T12:00:00.000Z",
    "status": "sent"
  },
  {
    "email": "miriamsmobileblooddraw@gmail.com",
    "name": "Miriam's Mobile blood draw LLC",
    "campaign": "survey-biggest-challenge-2026-03",
    "sentAt": "2026-03-10T12:00:00.000Z",
    "status": "sent"
  },
  {
    "email": "daniellenicole1817@gmail.com",
    "name": "Dominguez Diagnostic Solutions, LLC ",
    "campaign": "survey-biggest-challenge-2026-03",
    "sentAt": "2026-03-10T20:54:08.063Z",
    "status": "sent"
  },
  {
    "email": "karlyne@minustouchmobilephlebotomyservices.health",
    "name": "Minustouchmobilephlebotomyservices.health",
    "campaign": "fl-outreach-2026-03",
    "sentAt": "2026-03-13T01:30:16.043Z",
    "status": "sent"
  },
  {
    "email": "patellabs850@gmail.com",
    "name": "Patel Labs - Quest",
    "campaign": "fl-outreach-2026-03",
    "sentAt": "2026-03-13T01:30:16.114Z",
    "status": "sent"
  },
  {
    "email": "giftedhandsphlebotomy@gmail.com",
    "name": "Gifted Hands Phlebotomy Llc",
    "campaign": "fl-outreach-2026-03",
    "sentAt": "2026-03-13T01:30:16.215Z",
    "status": "sent"
  },
  {
    "email": "info@labexpressservices.com",
    "name": "Lab Express",
    "campaign": "fl-outreach-2026-03",
    "sentAt": "2026-03-13T01:30:16.319Z",
    "status": "sent"
  },
  {
    "email": "info@pleasantstick.com",
    "name": "Pleasant Stick Mobile Lab",
    "campaign": "fl-outreach-2026-03",
    "sentAt": "2026-03-13T01:30:16.419Z",
    "status": "sent"
  },
  {
    "email": "schedule@nrmobilelabs.com",
    "name": "NR Mobile Labs",
    "campaign": "fl-outreach-2026-03",
    "sentAt": "2026-03-13T01:30:16.522Z",
    "status": "sent"
  },
  {
    "email": "info@superiorcaremobile.com",
    "name": "Superior Care Mobile Phlebotomy LLC",
    "campaign": "fl-outreach-2026-03",
    "sentAt": "2026-03-13T01:30:16.624Z",
    "status": "sent"
  },
  {
    "email": "amp@amphlebotomy.com",
    "name": "A&M Labs & Wellness & Mobile Services",
    "campaign": "fl-outreach-2026-03",
    "sentAt": "2026-03-13T01:30:16.680Z",
    "status": "sent"
  },
  {
    "email": "admin@giftedhandsmobilephlebotomyllc.com",
    "name": "Gifted Hands Mobile Phlebotomy Llc",
    "campaign": "fl-outreach-2026-03",
    "sentAt": "2026-03-13T01:30:16.722Z",
    "status": "sent"
  }
]